MANIFEST.in
Makefile
README.rst
README.txt
project.ini
requirements.txt
setup.py
aiohug/__init__.py
aiohug/arguments.py
aiohug/directives.py
aiohug/shortcuts.py
aiohug.egg-info/PKG-INFO
aiohug.egg-info/SOURCES.txt
aiohug.egg-info/dependency_links.txt
aiohug.egg-info/requires.txt
aiohug.egg-info/top_level.txt
aiohug/tests/__init__.py
aiohug/tests/test_cast_arg.py
aiohug/tests/test_decorators.py
aiohug/tests/test_directives.py
aiohug/tests/test_error.py
aiohug/tests/test_get_arg.py
aiohug/tests/test_path_prefix.py
aiohug/tests/test_router.py
aiohug/tests/test_shortcuts.py
aiohug/tests/tests_default_args.py