Metadata-Version: 1.0
Name: aiohug
Version: 0.7.1
Summary: aiohug
Home-page: https://github.com/nonamenix/aiohug
Author: nonamenix
Author-email: nonamenix@gmail.com
License: UNKNOWN
Project-URL: Changelog, https://github.com/nonamenix/aiohug/blob/master/changelog.md
Project-URL: Issues, https://github.com/nonamenix/aiohug/issues
Keywords: aiohttp,aiohttp-server,aiohttp-swagger,hug,api,api-rest,rest,swagger,schema
Platform: UNKNOWN
